overpassforge/__init__.py
overpassforge/_utils.py
overpassforge/_variables.py
overpassforge/_visitors.py
overpassforge/base.py
overpassforge/builder.py
overpassforge/errors.py
overpassforge/filters.py
overpassforge/statements.py
overpassforge-0.4.3.dist-info/LICENSE
overpassforge-0.4.3.dist-info/METADATA
overpassforge-0.4.3.dist-info/WHEEL
overpassforge-0.4.3.dist-info/top_level.txt
overpassforge-0.4.3.dist-info/RECORD
