Metadata-Version: 2.1
Name: overpassforge
Version: 0.4.3
Summary: A library for generating OpenStreetMap's Overpass QL queries from Python objects.
Author-email: Krafpy <krafpy@gmail.com>
Project-URL: Homepage, https://github.com/Krafpy/Overpass-Forge
Project-URL: Bug Tracker, https://github.com/Krafpy/Overpass-Forge/issues
Project-URL: Documentation, https://overpassforge.readthedocs.io/en/latest
Classifier: Programming Language :: Python :: 3
Classifier: License :: OSI Approved :: MIT License
Classifier: Operating System :: OS Independent
Requires-Python: >=3.10
License-File: LICENSE
